{
  "timestamp": "2026-07-04T23:10:11.044297",
  "source_plates": [
    2,
    4,
    6,
    9,
    34,
    37
  ],
  "excluded_plates": [],
  "boundary_percentile": 90.0,
  "saturation_threshold": 0.15,
  "categorization_thresholds": {
    "ro_candidate_max_low": 40.0,
    "ro_candidate_min_high": 315.0,
    "gy_candidate_min": 60.0,
    "gy_candidate_max": 165.0,
    "buffer_zone_note": "Zona 40–60° dikategorikan 'other' dan tidak ikut derivasi. Berdasarkan transisi yellow-orange Munsell / FM-100 Hue Test."
  },
  "hue_boundaries": {
    "red_orange_max": 35,
    "red_orange_min": 330,
    "green_yellow_min": 65,
    "green_yellow_max": 75,
    "buffer_zone": [
      35,
      65
    ],
    "description": "red_orange: h <= 35 atau h >= 330 | green_yellow: 65 < h <= 75 | buffer/other: 35 < h <= 65"
  },
  "derived_raw": {
    "ro_max_raw": 35.73,
    "ro_min_raw": 330.0,
    "gy_min_raw": 64.22,
    "gy_max_raw": 76.29
  },
  "previous_hardcode": {
    "red_orange_max": 40,
    "red_orange_min": 330,
    "green_yellow_min": 55,
    "green_yellow_max": 160
  },
  "cluster_data": [
    {
      "plate_number": 2,
      "group": "confusion_line_validation",
      "cluster_idx": 2,
      "hue_360": 53.75,
      "saturation": 0.383,
      "value": 0.4357,
      "proportion": 0.3995,
      "hue_category": "other",
      "is_dominant": true
    },
    {
      "plate_number": 2,
      "group": "confusion_line_validation",
      "cluster_idx": 1,
      "hue_360": 49.46,
      "saturation": 0.2481,
      "value": 0.8601,
      "proportion": 0.3187,
      "hue_category": "other",
      "is_dominant": false
    },
    {
      "plate_number": 2,
      "group": "confusion_line_validation",
      "cluster_idx": 0,
      "hue_360": 36.18,
      "saturation": 0.5416,
      "value": 0.8099,
      "proportion": 0.2818,
      "hue_category": "red_orange_candidate",
      "is_dominant": false
    },
    {
      "plate_number": 4,
      "group": "confusion_line_validation",
      "cluster_idx": 1,
      "hue_360": 56.2,
      "saturation": 0.4121,
      "value": 0.4635,
      "proportion": 0.5401,
      "hue_category": "other",
      "is_dominant": true
    },
    {
      "plate_number": 4,
      "group": "confusion_line_validation",
      "cluster_idx": 0,
      "hue_360": 53.41,
      "saturation": 0.2564,
      "value": 0.897,
      "proportion": 0.3282,
      "hue_category": "other",
      "is_dominant": false
    },
    {
      "plate_number": 4,
      "group": "confusion_line_validation",
      "cluster_idx": 2,
      "hue_360": 13.71,
      "saturation": 0.6079,
      "value": 0.944,
      "proportion": 0.1316,
      "hue_category": "red_orange_candidate",
      "is_dominant": false
    },
    {
      "plate_number": 6,
      "group": "confusion_line_validation",
      "cluster_idx": 1,
      "hue_360": 16.38,
      "saturation": 0.6748,
      "value": 0.9422,
      "proportion": 0.5449,
      "hue_category": "red_orange_candidate",
      "is_dominant": true
    },
    {
      "plate_number": 6,
      "group": "confusion_line_validation",
      "cluster_idx": 0,
      "hue_360": 31.71,
      "saturation": 0.3163,
      "value": 0.9544,
      "proportion": 0.3614,
      "hue_category": "red_orange_candidate",
      "is_dominant": false
    },
    {
      "plate_number": 6,
      "group": "confusion_line_validation",
      "cluster_idx": 3,
      "hue_360": 64.22,
      "saturation": 0.3769,
      "value": 0.556,
      "proportion": 0.0744,
      "hue_category": "green_yellow_candidate",
      "is_dominant": false
    },
    {
      "plate_number": 6,
      "group": "confusion_line_validation",
      "cluster_idx": 2,
      "hue_360": 354.76,
      "saturation": 0.5065,
      "value": 0.8515,
      "proportion": 0.0194,
      "hue_category": "red_orange_candidate",
      "is_dominant": false
    },
    {
      "plate_number": 9,
      "group": "confusion_line_validation",
      "cluster_idx": 0,
      "hue_360": 17.57,
      "saturation": 0.6597,
      "value": 0.9096,
      "proportion": 0.4786,
      "hue_category": "red_orange_candidate",
      "is_dominant": true
    },
    {
      "plate_number": 9,
      "group": "confusion_line_validation",
      "cluster_idx": 2,
      "hue_360": 43.61,
      "saturation": 0.3155,
      "value": 0.9572,
      "proportion": 0.3824,
      "hue_category": "other",
      "is_dominant": false
    },
    {
      "plate_number": 9,
      "group": "confusion_line_validation",
      "cluster_idx": 1,
      "hue_360": 69.96,
      "saturation": 0.3682,
      "value": 0.5194,
      "proportion": 0.1314,
      "hue_category": "green_yellow_candidate",
      "is_dominant": false
    },
    {
      "plate_number": 9,
      "group": "confusion_line_validation",
      "cluster_idx": 3,
      "hue_360": 356.62,
      "saturation": 0.6359,
      "value": 0.6932,
      "proportion": 0.0076,
      "hue_category": "red_orange_candidate",
      "is_dominant": false
    },
    {
      "plate_number": 10,
      "group": "unclassified",
      "cluster_idx": 1,
      "hue_360": 69.59,
      "saturation": 0.4072,
      "value": 0.5288,
      "proportion": 0.4149,
      "hue_category": "green_yellow_candidate",
      "is_dominant": true
    },
    {
      "plate_number": 10,
      "group": "unclassified",
      "cluster_idx": 2,
      "hue_360": 49.57,
      "saturation": 0.2585,
      "value": 0.8713,
      "proportion": 0.3387,
      "hue_category": "other",
      "is_dominant": false
    },
    {
      "plate_number": 10,
      "group": "unclassified",
      "cluster_idx": 0,
      "hue_360": 36.05,
      "saturation": 0.5805,
      "value": 0.9036,
      "proportion": 0.2464,
      "hue_category": "red_orange_candidate",
      "is_dominant": false
    },
    {
      "plate_number": 12,
      "group": "unclassified",
      "cluster_idx": 0,
      "hue_360": 51.74,
      "saturation": 0.2753,
      "value": 0.8943,
      "proportion": 0.3897,
      "hue_category": "other",
      "is_dominant": true
    },
    {
      "plate_number": 12,
      "group": "unclassified",
      "cluster_idx": 1,
      "hue_360": 58.37,
      "saturation": 0.4514,
      "value": 0.4971,
      "proportion": 0.3629,
      "hue_category": "other",
      "is_dominant": false
    },
    {
      "plate_number": 12,
      "group": "unclassified",
      "cluster_idx": 2,
      "hue_360": 33.8,
      "saturation": 0.5957,
      "value": 0.864,
      "proportion": 0.2474,
      "hue_category": "red_orange_candidate",
      "is_dominant": false
    },
    {
      "plate_number": 15,
      "group": "unclassified",
      "cluster_idx": 1,
      "hue_360": 20.73,
      "saturation": 0.6663,
      "value": 0.9408,
      "proportion": 0.5483,
      "hue_category": "red_orange_candidate",
      "is_dominant": true
    },
    {
      "plate_number": 15,
      "group": "unclassified",
      "cluster_idx": 0,
      "hue_360": 33.0,
      "saturation": 0.3314,
      "value": 0.9531,
      "proportion": 0.3669,
      "hue_category": "red_orange_candidate",
      "is_dominant": false
    },
    {
      "plate_number": 15,
      "group": "unclassified",
      "cluster_idx": 3,
      "hue_360": 82.3,
      "saturation": 0.364,
      "value": 0.5006,
      "proportion": 0.06,
      "hue_category": "green_yellow_candidate",
      "is_dominant": false
    },
    {
      "plate_number": 15,
      "group": "unclassified",
      "cluster_idx": 2,
      "hue_360": 355.83,
      "saturation": 0.5844,
      "value": 0.9027,
      "proportion": 0.0249,
      "hue_category": "red_orange_candidate",
      "is_dominant": false
    },
    {
      "plate_number": 20,
      "group": "unclassified",
      "cluster_idx": 1,
      "hue_360": 48.62,
      "saturation": 0.4526,
      "value": 0.5209,
      "proportion": 0.4439,
      "hue_category": "other",
      "is_dominant": true
    },
    {
      "plate_number": 20,
      "group": "unclassified",
      "cluster_idx": 0,
      "hue_360": 12.36,
      "saturation": 0.7045,
      "value": 0.9541,
      "proportion": 0.2991,
      "hue_category": "red_orange_candidate",
      "is_dominant": false
    },
    {
      "plate_number": 20,
      "group": "unclassified",
      "cluster_idx": 2,
      "hue_360": 36.1,
      "saturation": 0.2696,
      "value": 0.892,
      "proportion": 0.2481,
      "hue_category": "red_orange_candidate",
      "is_dominant": false
    },
    {
      "plate_number": 20,
      "group": "unclassified",
      "cluster_idx": 3,
      "hue_360": 354.76,
      "saturation": 0.5357,
      "value": 0.8128,
      "proportion": 0.0089,
      "hue_category": "red_orange_candidate",
      "is_dominant": false
    },
    {
      "plate_number": 22,
      "group": "hue_mapping_reference",
      "cluster_idx": 0,
      "hue_360": 28.12,
      "saturation": 0.3133,
      "value": 0.5922,
      "proportion": 0.7931,
      "hue_category": "red_orange_candidate",
      "is_dominant": true
    },
    {
      "plate_number": 22,
      "group": "hue_mapping_reference",
      "cluster_idx": 1,
      "hue_360": 325.6,
      "saturation": 0.4595,
      "value": 0.4903,
      "proportion": 0.2069,
      "hue_category": "red_orange_candidate",
      "is_dominant": false
    },
    {
      "plate_number": 23,
      "group": "hue_mapping_reference",
      "cluster_idx": 0,
      "hue_360": 28.1,
      "saturation": 0.3136,
      "value": 0.5842,
      "proportion": 0.7788,
      "hue_category": "red_orange_candidate",
      "is_dominant": true
    },
    {
      "plate_number": 23,
      "group": "hue_mapping_reference",
      "cluster_idx": 1,
      "hue_360": 322.44,
      "saturation": 0.4327,
      "value": 0.4656,
      "proportion": 0.2213,
      "hue_category": "red_orange_candidate",
      "is_dominant": false
    },
    {
      "plate_number": 24,
      "group": "hue_mapping_reference",
      "cluster_idx": 1,
      "hue_360": 27.14,
      "saturation": 0.2503,
      "value": 0.4617,
      "proportion": 0.5874,
      "hue_category": "red_orange_candidate",
      "is_dominant": true
    },
    {
      "plate_number": 24,
      "group": "hue_mapping_reference",
      "cluster_idx": 3,
      "hue_360": 9.66,
      "saturation": 0.4943,
      "value": 0.9442,
      "proportion": 0.1537,
      "hue_category": "red_orange_candidate",
      "is_dominant": false
    },
    {
      "plate_number": 24,
      "group": "hue_mapping_reference",
      "cluster_idx": 2,
      "hue_360": 351.13,
      "saturation": 0.6363,
      "value": 0.7564,
      "proportion": 0.1349,
      "hue_category": "red_orange_candidate",
      "is_dominant": false
    },
    {
      "plate_number": 24,
      "group": "hue_mapping_reference",
      "cluster_idx": 0,
      "hue_360": 302.55,
      "saturation": 0.2256,
      "value": 0.2364,
      "proportion": 0.124,
      "hue_category": "other",
      "is_dominant": false
    },
    {
      "plate_number": 26,
      "group": "hue_mapping_reference",
      "cluster_idx": 1,
      "hue_360": 24.99,
      "saturation": 0.3397,
      "value": 0.5972,
      "proportion": 0.7629,
      "hue_category": "red_orange_candidate",
      "is_dominant": true
    },
    {
      "plate_number": 26,
      "group": "hue_mapping_reference",
      "cluster_idx": 0,
      "hue_360": 332.21,
      "saturation": 0.4588,
      "value": 0.5129,
      "proportion": 0.2371,
      "hue_category": "red_orange_candidate",
      "is_dominant": false
    },
    {
      "plate_number": 27,
      "group": "hue_mapping_reference",
      "cluster_idx": 1,
      "hue_360": 31.91,
      "saturation": 0.2714,
      "value": 0.4181,
      "proportion": 0.4577,
      "hue_category": "red_orange_candidate",
      "is_dominant": true
    },
    {
      "plate_number": 27,
      "group": "hue_mapping_reference",
      "cluster_idx": 0,
      "hue_360": 16.16,
      "saturation": 0.4548,
      "value": 0.9317,
      "proportion": 0.2943,
      "hue_category": "red_orange_candidate",
      "is_dominant": false
    },
    {
      "plate_number": 27,
      "group": "hue_mapping_reference",
      "cluster_idx": 2,
      "hue_360": 351.81,
      "saturation": 0.6739,
      "value": 0.7126,
      "proportion": 0.1435,
      "hue_category": "red_orange_candidate",
      "is_dominant": false
    },
    {
      "plate_number": 27,
      "group": "hue_mapping_reference",
      "cluster_idx": 3,
      "hue_360": 296.14,
      "saturation": 0.2401,
      "value": 0.2338,
      "proportion": 0.1045,
      "hue_category": "other",
      "is_dominant": false
    },
    {
      "plate_number": 28,
      "group": "unclassified",
      "cluster_idx": 2,
      "hue_360": 52.15,
      "saturation": 0.4504,
      "value": 0.516,
      "proportion": 0.4778,
      "hue_category": "other",
      "is_dominant": true
    },
    {
      "plate_number": 28,
      "group": "unclassified",
      "cluster_idx": 0,
      "hue_360": 42.07,
      "saturation": 0.2704,
      "value": 0.8817,
      "proportion": 0.2619,
      "hue_category": "other",
      "is_dominant": false
    },
    {
      "plate_number": 28,
      "group": "unclassified",
      "cluster_idx": 1,
      "hue_360": 15.32,
      "saturation": 0.7015,
      "value": 0.9502,
      "proportion": 0.2604,
      "hue_category": "red_orange_candidate",
      "is_dominant": false
    },
    {
      "plate_number": 30,
      "group": "unclassified",
      "cluster_idx": 1,
      "hue_360": 22.65,
      "saturation": 0.6718,
      "value": 0.9337,
      "proportion": 0.4536,
      "hue_category": "red_orange_candidate",
      "is_dominant": true
    },
    {
      "plate_number": 30,
      "group": "unclassified",
      "cluster_idx": 0,
      "hue_360": 38.18,
      "saturation": 0.3027,
      "value": 0.9462,
      "proportion": 0.3311,
      "hue_category": "red_orange_candidate",
      "is_dominant": false
    },
    {
      "plate_number": 30,
      "group": "unclassified",
      "cluster_idx": 2,
      "hue_360": 81.72,
      "saturation": 0.3702,
      "value": 0.5151,
      "proportion": 0.1885,
      "hue_category": "green_yellow_candidate",
      "is_dominant": false
    },
    {
      "plate_number": 30,
      "group": "unclassified",
      "cluster_idx": 3,
      "hue_360": 355.07,
      "saturation": 0.5788,
      "value": 0.868,
      "proportion": 0.0267,
      "hue_category": "red_orange_candidate",
      "is_dominant": false
    },
    {
      "plate_number": 31,
      "group": "unclassified",
      "cluster_idx": 0,
      "hue_360": 26.67,
      "saturation": 0.6785,
      "value": 0.9452,
      "proportion": 0.5086,
      "hue_category": "red_orange_candidate",
      "is_dominant": true
    },
    {
      "plate_number": 31,
      "group": "unclassified",
      "cluster_idx": 1,
      "hue_360": 42.99,
      "saturation": 0.3142,
      "value": 0.9593,
      "proportion": 0.3588,
      "hue_category": "other",
      "is_dominant": false
    },
    {
      "plate_number": 31,
      "group": "unclassified",
      "cluster_idx": 2,
      "hue_360": 77.91,
      "saturation": 0.3861,
      "value": 0.5481,
      "proportion": 0.1229,
      "hue_category": "green_yellow_candidate",
      "is_dominant": false
    },
    {
      "plate_number": 31,
      "group": "unclassified",
      "cluster_idx": 3,
      "hue_360": 356.9,
      "saturation": 0.6327,
      "value": 0.8612,
      "proportion": 0.0097,
      "hue_category": "red_orange_candidate",
      "is_dominant": false
    },
    {
      "plate_number": 32,
      "group": "unclassified",
      "cluster_idx": 0,
      "hue_360": 47.16,
      "saturation": 0.2741,
      "value": 0.8926,
      "proportion": 0.3342,
      "hue_category": "other",
      "is_dominant": true
    },
    {
      "plate_number": 32,
      "group": "unclassified",
      "cluster_idx": 1,
      "hue_360": 53.29,
      "saturation": 0.4324,
      "value": 0.5211,
      "proportion": 0.3197,
      "hue_category": "other",
      "is_dominant": false
    },
    {
      "plate_number": 32,
      "group": "unclassified",
      "cluster_idx": 2,
      "hue_360": 28.53,
      "saturation": 0.631,
      "value": 0.887,
      "proportion": 0.2954,
      "hue_category": "red_orange_candidate",
      "is_dominant": false
    },
    {
      "plate_number": 32,
      "group": "unclassified",
      "cluster_idx": 3,
      "hue_360": 182.94,
      "saturation": 0.2357,
      "value": 0.4819,
      "proportion": 0.0506,
      "hue_category": "other",
      "is_dominant": false
    },
    {
      "plate_number": 34,
      "group": "confusion_line_validation",
      "cluster_idx": 2,
      "hue_360": 19.88,
      "saturation": 0.6607,
      "value": 0.9116,
      "proportion": 0.513,
      "hue_category": "red_orange_candidate",
      "is_dominant": true
    },
    {
      "plate_number": 34,
      "group": "confusion_line_validation",
      "cluster_idx": 3,
      "hue_360": 35.73,
      "saturation": 0.3037,
      "value": 0.9484,
      "proportion": 0.3339,
      "hue_category": "red_orange_candidate",
      "is_dominant": false
    },
    {
      "plate_number": 34,
      "group": "confusion_line_validation",
      "cluster_idx": 0,
      "hue_360": 78.4,
      "saturation": 0.3634,
      "value": 0.5431,
      "proportion": 0.1373,
      "hue_category": "green_yellow_candidate",
      "is_dominant": false
    },
    {
      "plate_number": 34,
      "group": "confusion_line_validation",
      "cluster_idx": 1,
      "hue_360": 355.45,
      "saturation": 0.4836,
      "value": 0.7931,
      "proportion": 0.0159,
      "hue_category": "red_orange_candidate",
      "is_dominant": false
    },
    {
      "plate_number": 37,
      "group": "confusion_line_validation",
      "cluster_idx": 1,
      "hue_360": 57.84,
      "saturation": 0.4322,
      "value": 0.4683,
      "proportion": 0.5593,
      "hue_category": "other",
      "is_dominant": true
    },
    {
      "plate_number": 37,
      "group": "confusion_line_validation",
      "cluster_idx": 2,
      "hue_360": 53.89,
      "saturation": 0.2742,
      "value": 0.879,
      "proportion": 0.2921,
      "hue_category": "other",
      "is_dominant": false
    },
    {
      "plate_number": 37,
      "group": "confusion_line_validation",
      "cluster_idx": 0,
      "hue_360": 16.84,
      "saturation": 0.6429,
      "value": 0.939,
      "proportion": 0.1486,
      "hue_category": "red_orange_candidate",
      "is_dominant": false
    }
  ]
}